SimpleAciUiLogServer/__init__.py
SimpleAciUiLogServer/SimpleAciUiLogServer.py
SimpleAciUiLogServer/version.py
SimpleAciUiLogServer-1.1.3.data/scripts/SimpleAciUiLogServer.py
SimpleAciUiLogServer-1.1.3.dist-info/DESCRIPTION.rst
SimpleAciUiLogServer-1.1.3.dist-info/entry_points.txt
SimpleAciUiLogServer-1.1.3.dist-info/METADATA
SimpleAciUiLogServer-1.1.3.dist-info/metadata.json
SimpleAciUiLogServer-1.1.3.dist-info/RECORD
SimpleAciUiLogServer-1.1.3.dist-info/top_level.txt
SimpleAciUiLogServer-1.1.3.dist-info/WHEEL
