Metadata-Version: 2.0
Name: SimpleAciUiLogServer
Version: 1.1.3
Summary: A remote API Inspector written in Python
Home-page: https://github.com/datacenter/SimpleAciUiLogServer
Author: Mike Timm
Author-email: mtimm@cisco.com
License: SimpleAciUiLogServer
